odoo10_addon_invader_payment-10.0.2.0.1-py3.8-nspkg.pth
odoo/addons/invader_payment/README.rst
odoo/addons/invader_payment/__init__.py
odoo/addons/invader_payment/__manifest__.py
odoo/addons/invader_payment/models/__init__.py
odoo/addons/invader_payment/models/account_payment_mode.py
odoo/addons/invader_payment/models/invader_payable.py
odoo/addons/invader_payment/models/payment_transaction.py
odoo/addons/invader_payment/readme/CONTRIBUTORS.rst
odoo/addons/invader_payment/readme/DESCRIPTION.rst
odoo/addons/invader_payment/services/__init__.py
odoo/addons/invader_payment/services/invader_payment_service.py
odoo/addons/invader_payment/static/description/index.html
odoo/addons/invader_payment/views/account_payment_mode.xml
odoo10_addon_invader_payment-10.0.2.0.1.dist-info/METADATA
odoo10_addon_invader_payment-10.0.2.0.1.dist-info/WHEEL
odoo10_addon_invader_payment-10.0.2.0.1.dist-info/namespace_packages.txt
odoo10_addon_invader_payment-10.0.2.0.1.dist-info/top_level.txt
odoo10_addon_invader_payment-10.0.2.0.1.dist-info/RECORD
