Metadata-Version: 2.1
Name: odoo10-addon-invader-payment
Version: 10.0.2.0.1
Summary: Payment integration for Shopinvader
Home-page: https://github.com/shopinvader/odoo-shopinvader-payment
Author: ACSONE SA/NV
License: AGPL-3
Platform: UNKNOWN
Classifier: Programming Language :: Python
Classifier: Framework :: Odoo
Classifier: License :: OSI Approved :: GNU Affero General Public License v3
Requires-Python: ~=2.7
Requires-Dist: cerberus
Requires-Dist: odoo10-addon-account-payment-mode
Requires-Dist: odoo10-addon-component
Requires-Dist: odoo10-addon-component-event
Requires-Dist: odoo (<10.1dev,>=10.0)
Requires-Dist: unidecode
